sci_util/__init__.py
sci_util/__version__.py
sci_util/common/__init__.py
sci_util/common/decorator.py
sci_util/file_util/__init__.py
sci_util/file_util/csv_cache_read_util.py
sci_util/list_util/__init__.py
sci_util/list_util/split_util.py
sci_util/log_util/Logger.py
sci_util/log_util/__init__.py
sci_util/log_util/stdout.py
sci_util/pd/__init__.py
sci_util/pd/csv.py
sci_util/pd/fn.py
sci_util/string_util/__init__.py
sci_util/string_util/string_preprocess_util.py
sci_util/test_util/__init__.py
sci_util/test_util/debug_util.py
sci_util-1.2.7.dist-info/LICENSE
sci_util-1.2.7.dist-info/METADATA
sci_util-1.2.7.dist-info/WHEEL
sci_util-1.2.7.dist-info/top_level.txt
sci_util-1.2.7.dist-info/RECORD
